MightyMosaic/MightyMosaic.py
MightyMosaic/__init__.py
MightyMosaic-1.2.3.dist-info/LICENSE
MightyMosaic-1.2.3.dist-info/METADATA
MightyMosaic-1.2.3.dist-info/WHEEL
MightyMosaic-1.2.3.dist-info/top_level.txt
MightyMosaic-1.2.3.dist-info/RECORD
