Metadata-Version: 2.1
Name: MightyMosaic
Version: 1.2.3
Summary: Create mosaics with overlapping tiles
Home-page: https://github.com/Rignak/MightyMosaic
Author: Aurélien COLIN
Author-email: aureliencolin@hotmail.com
License: UNKNOWN
Platform: UNKNOWN
Classifier: Programming Language :: Python :: 3.6
Classifier: License :: OSI Approved :: GNU General Public License v3 (GPLv3)
Requires-Python: >=3.6
Requires-Dist: tqdm (>=4.32.1)
